Workbook

Sheet DEPO
B1: Sr. No. | C1: Banks | D1: Deposits | G1: Investments | J1: Advances
B2: I | C2: NATIONALISED BANKS | D2: 2023 | E2: 2024 | F2: 2025 | G2: 2023 | H2: 2024 | I2: 2025 | J2: 2023 | K2: 2024 | L2: 2025
B3: 1 | C3: Bank of Baroda | D3: 1203687.8 | E3: 1335136.4 | F3: 1472034.9 | G3: 362485.36 | H3: 369816.84 | I3: 385398.45 | J3: 940998.27 | K3: 1065781.7 | L3: 1209557.9
B4: 2 | C4: Bank of India | D4: 669586 | E4: 737920.21 | F4: 816541.49 | G4: 204398 | H4: 227144.47 | I4: 259111.8 | J4: 485899.64 | K4: 563144.67 | L4: 649657.04
B5: 3 | C5: Bank of Maharashtra | D5: 234082.68 | E5: 270747.17 | F5: 307142.6 | G5: 68866.95 | H5: 68274.12 | I5: 82004.79 | J5: 171220.67 | K5: 200239.88 | L5: 236083.8
B6: 4 | C6: Canara Bank | D6: 1179218.6 | E6: 1312366.6 | F6: 1456883.2 | G6: 319038.45 | H6: 357454.42 | I6: 380343.4 | J6: 830672.55 | K6: 931612.83 | L6: 1049155
B7: 5 | C7: Central Bank of India | D7: 359296.47 | E7: 385011.32 | F7: 412697.14 | G7: 136583.48 | H7: 143923.49 | I7: 141435.25 | J7: 202984.31 | K7: 243406.28 | L7: 282419.87
B8: 6 | C8: Indian Bank | D8: 621165.76 | E8: 688000 | F8: 737153.56 | G8: 185988.25 | H8: 212554.48 | I8: 225303.12 | J8: 449296.73 | K8: 514889.07 | L8: 571071.19
B9: 7 | C9: Indian Overseas Bank | D9: 260883.29 | E9: 285905.38 | F9: 311938.82 | G9: 94170.41 | H9: 99632.08 | I9: 111044.84 | J9: 178052.57 | K9: 213318.81 | L9: 245555.17
B10: 8 | C10: Punjab & Sind Bank | D10: 109665.49 | E10: 119409.55 | F10: 129774.02 | G10: 44838.42 | H10: 49599.16 | I10: 46912.31 | J10: 76819.43 | K10: 82736.38 | L10: 97299.9
B11: 9 | C11: Punjab National Bank | D11: 1281163.1 | E11: 1369712.8 | F11: 1566623.3 | G11: 395996.72 | H11: 420318.21 | I11: 497311.25 | J11: 830833.98 | K11: 934430.59 | L11: 1077474.6
B12: 10 | C12: UCO Bank | D12: 249337.74 | E12: 263129.77 | F12: 293542.18 | G12: 95169.35 | H12: 92904.4 | I12: 94272.49 | J12: 155870.18 | K12: 182021.87 | L12: 215134.58
B13: 11 | C13: Union Bank of India | D13: 1117716.3 | E13: 1221528.4 | F13: 1309749.5 | G13: 339299.05 | H13: 337903.53 | I13: 354381.4 | J13: 761845.46 | K13: 870776.09 | L13: 953513.34
B14: 12 | C14: State Bank of India (SBI) | D14: 4423777.8 | E14: 4916077 | F14: 5382190 | G14: 1570366.2 | H14: 1671340 | I14: 1690573 | J14: 3199269.3 | K14: 3703971 | L14: 4163312

Sheet Assets
B1: Sr. No. | C1: Banks | D1: Total Assets | G1: Gross NPA | J1: Net NPA
B2: I | C2: NATIONALISED BANKS | D2: 2023 | E2: 2024 | F2: 2025 | G2: 2023 | H2: 2024 | I2: 2025 | J2: 2023 | K2: 2024 | L2: 2025
B3: 1 | C3: Bank of Baroda | D3: 1458561.5 | E3: 1585797.1 | F3: 1781247.3 | G3: 36763.68 | H3: 31833.63 | I3: 27834.88 | J3: 8384.32 | K3: 7213.34 | L3: 6994.24
B4: 2 | C4: Bank of India | D4: 815556 | E4: 912597.92 | F4: 1042581.9 | G4: 37685.56 | H4: 29182.77 | I4: 21748.89 | J4: 8053.61 | K4: 6845.25 | L4: 5358.49
B5: 3 | C5: Bank of Maharashtra | D5: 267651.39 | E5: 307137.86 | F5: 369142.15 | G5: 4334 | H5: 3833.05 | I5: 4184.52 | J5: 435.18 | K5: 408.99 | L5: 431.78
B6: 4 | C6: Canara Bank | D6: 1345732.2 | E6: 1491540.7 | F6: 1682849.6 | G6: 46159.51 | H6: 40604.57 | I6: 31530.03 | J6: 14349.33 | K6: 11822.83 | L6: 7353.31
B7: 5 | C7: Central Bank of India | D7: 406165.49 | E7: 446672.69 | F7: 479128.13 | G7: 18436.48 | H7: 11340.34 | I7: 9224.78 | J7: 3627.22 | K7: 3001.95 | L7: 1543.26
B8: 6 | C8: Indian Bank | D8: 710500.73 | E8: 792619.12 | F8: 873410.66 | G8: 28179.53 | H8: 21106.31 | I8: 18178.86 | J8: 4043.07 | K8: 2222.58 | L8: 1109.56
B9: 7 | C9: Indian Overseas Bank | D9: 313745.82 | E9: 352033.62 | F9: 395014.94 | G9: 14071.55 | H9: 6794.43 | I9: 5347.72 | J9: 3266.01 | K9: 1216.86 | L9: 911.86
B10: 8 | C10: Punjab & Sind Bank | D10: 136454.52 | E10: 147656.53 | F10: 161815.17 | G10: 5648.21 | H10: 4665.35 | I10: 3370.6 | J10: 1411.5 | K10: 1350.46 | L10: 937.07
B11: 9 | C11: Punjab National Bank | D11: 1461831.4 | E11: 1561835 | F11: 1818170.7 | G11: 77327.67 | H11: 56343.05 | I11: 44081.6 | J11: 22585.04 | K11: 6798.77 | L11: 4290.55
B12: 10 | C12: UCO Bank | D12: 300862.99 | E12: 323691.45 | F12: 362481.08 | G12: 7726.46 | H12: 6463.3 | I12: 5918.54 | J12: 2018.02 | K12: 1621.64 | L12: 1068.1
B13: 11 | C13: Union Bank of India | D13: 1280752.4 | E13: 1391957.6 | F13: 1499855.7 | G13: 60987.29 | H13: 43097.73 | I13: 35350.38 | J13: 12927.44 | K13: 8989.92 | L13: 5969.29
B14: 12 | C14: State Bank of India (SBI) | D14: 5516978.5 | E14: 6179694 | F14: 6676053 | G14: 90927.78 | H14: 84276 | I14: 76880 | J14: 21466.64 | K14: 21051 | L14: 19667

Sheet INCOME
C1: Sr. No. | D1: Banks | E1: Interest Income | H1: Other Income | K1: Total Income
C2: I | D2: NATIONALISED BANKS | E2: 2023 | F2: 2024 | G2: 2025 | H2: 2023 | I2: 2024 | J2: 2025 | K2: 2023 | L2: 2024 | M2: 2025
C3: 1 | D3: Bank of Baroda | E3: 89588.54 | F3: 112605.94 | G3: 121441.64 | H3: 10025.84 | I3: 14495.37 | J3: 16647.33 | K3: =E3+H3 -> 99614.38 | L3: =F3+I3 -> 127101.31 | M3: =G3+J3 -> 138088.97
C4: 2 | D4: Bank of India | E4: 47647.72 | F4: 60709.49 | G4: 70826.3 | H4: 7099.89 | I4: 6094.85 | J4: 8993.62 | K4: =E4+H4 -> 54747.61 | L4: =F4+I4 -> 66804.34 | M4: =G4+J4 -> 79819.92
C5: 3 | D5: Bank of Maharashtra | E5: 15898.46 | F5: 20494.69 | G5: 24947.45 | H5: 2280.27 | I5: 2997.87 | J5: 3454.17 | K5: =E5+H5 -> 18178.73 | L5: =F5+I5 -> 23492.56 | M5: =G5+J5 -> 28401.62
C6: 4 | D6: Canara Bank | E6: 84424.78 | F6: 108687.93 | G6: 119755.07 | H6: 18762.2 | I6: 18966.44 | J6: 22452.8 | K6: =E6+H6 -> 103186.98 | L6: =F6+I6 -> 127654.37 | M6: =G6+J6 -> 142207.87
C7: 5 | D7: Central Bank of India | E7: 25541.89 | F7: 30722.23 | G7: 33665.85 | H7: 4083.71 | I7: 4711.28 | J7: 5854.59 | K7: =E7+H7 -> 29625.6 | L7: =F7+I7 -> 35433.51 | M7: =G7+J7 -> 39520.44
C8: 6 | D8: Indian Bank | E8: 44942.21 | F8: 55614.78 | G8: 62002.16 | H8: 7143.06 | I8: 7866.72 | J8: 9223.48 | K8: =E8+H8 -> 52085.27 | L8: =F8+I8 -> 63481.5 | M8: =G8+J8 -> 71225.64
C9: 7 | D9: Indian Overseas Bank | E9: 19400.33 | F9: 24049.73 | G9: 28131.01 | H9: 4108.75 | I9: 5656.26 | J9: 5545.07 | K9: =E9+H9 -> 23509.08 | L9: =F9+I9 -> 29705.99 | M9: =G9+J9 -> 33676.08
C10: 8 | D10: Punjab & Sind Bank | E10: 7992.73 | F10: 9693.98 | G10: 11481.3 | H10: 939.96 | I10: 1221.47 | J10: 1567.65 | K10: =E10+H10 -> 8932.69 | L10: =F10+I10 -> 10915.45 | M10: =G10+J10 -> 13048.95
C11: 9 | D11: Punjab National Bank | E11: 85144.11 | F11: 106901.62 | G11: 121760.73 | H11: 12142.53 | I11: 13383.54 | J11: 16309.37 | K11: =E11+H11 -> 97286.64 | L11: =F11+I11 -> 120285.16 | M11: =G11+J11 -> 138070.1
C12: 10 | D12: UCO Bank | E12: 17650.52 | F12: 21854.34 | G12: 25066.9 | H12: 2508.46 | I12: 3265.53 | J12: 4406.63 | K12: =E12+H12 -> 20158.98 | L12: =F12+I12 -> 25119.87 | M12: =G12+J12 -> 29473.53
C13: 11 | D13: Union Bank of India | E13: 80743.34 | F13: 99777.96 | G13: 107725.97 | H13: 14633.15 | I13: 16080.19 | J13: 19812.92 | K13: =E13+H13 -> 95376.49 | L13: =F13+I13 -> 115858.15 | M13: =G13+J13 -> 127538.89
C14: 12 | D14: State Bank of India (SBI) | E14: 332103.06 | F14: 415131 | G14: 462489 | H14: 36615.59 | I14: 51682 | J14: 61683 | K14: =E14+H14 -> 368718.65 | L14: =F14+I14 -> 466813 | M14: =G14+J14 -> 524172

Sheet EXP
B1: Sr. No. | C1: Banks | D1: Interest Expended | G1: Operating Expenses | J1: Total Expenditure*
B2: I | C2: NATIONALISED BANKS | D2: 2023 | E2: 2024 | F2: 2025 | G2: 2023 | H2: 2024 | I2: 2025 | J2: 2023 | K2: 2024 | L2: 2025
B3: 1 | C3: Bank of Baroda | D3: 48232.53 | E3: 67884.41 | F3: 75782.96 | G3: 24518.31 | H3: 28251.68 | I3: 29871.38 | J3: =D3+G3 -> 72750.84 | K3: =E3+H3 -> 96136.09 | L3: =F3+I3 -> 105654.34
B4: 2 | C4: Bank of India | D4: 27372.82 | E4: 37656.57 | F4: 46432.35 | G4: 13982.17 | H4: 15079.16 | I4: 16975.46 | J4: =D4+G4 -> 41354.99 | K4: =E4+H4 -> 52735.73 | L4: =F4+I4 -> 63407.81
B5: 3 | C5: Bank of Maharashtra | D5: 8157.68 | E5: 10672.84 | F5: 13281.88 | G5: 3921.84 | H5: 4814.38 | I5: 5800.71 | J5: =D5+G5 -> 12079.52 | K5: =E5+H5 -> 15487.22 | L5: =F5+I5 -> 19082.59
B6: 4 | C6: Canara Bank | D6: 52989.49 | E6: 72121.99 | F6: 82683.11 | G6: 22481.48 | H6: 26119.79 | I6: 28134.5 | J6: =D6+G6 -> 75470.97 | K6: =E6+H6 -> 98241.78 | L6: =F6+I6 -> 110817.61
B7: 5 | C7: Central Bank of India | D7: 13855.1 | E7: 17825.91 | F7: 19768.96 | G7: 8886.74 | H7: 10244.92 | I7: 11627.17 | J7: =D7+G7 -> 22741.84 | K7: =E7+H7 -> 28070.83 | L7: =F7+I7 -> 31396.13
B8: 6 | C8: Indian Bank | D8: 24716.75 | E8: 32341.49 | F8: 36825.79 | G8: 12097.9 | H8: 14300.46 | I8: 15401.65 | J8: =D8+G8 -> 36814.65 | K8: =E8+H8 -> 46641.95 | L8: =F8+I8 -> 52227.44
B9: 7 | C9: Indian Overseas Bank | D9: 11145.44 | E9: 14220.32 | F9: 17240.8 | G9: 6421.46 | H9: 8721.91 | I9: 7747.27 | J9: =D9+G9 -> 17566.9 | K9: =E9+H9 -> 22942.23 | L9: =F9+I9 -> 24988.07
B10: 8 | C10: Punjab & Sind Bank | D10: 5019.35 | E10: 6852.94 | F10: 7697.64 | G10: 2463.4 | H10: 2931.57 | I10: 3276.39 | J10: =D10+G10 -> 7482.75 | K10: =E10+H10 -> 9784.51 | L10: =F10+I10 -> 10974.03
B11: 9 | C11: Punjab National Bank | D11: 50652.48 | E11: 66818.55 | F11: 78978.56 | G11: 24105.41 | H11: 28535.8 | I11: 32260.87 | J11: =D11+G11 -> 74757.89 | K11: =E11+H11 -> 95354.35 | L11: =F11+I11 -> 111239.43
B12: 10 | C12: UCO Bank | D12: 10307.39 | E12: 13753.56 | F12: 15436.83 | G12: 5510.92 | H12: 6790.07 | I12: 7999.41 | J12: =D12+G12 -> 15818.31 | K12: =E12+H12 -> 20543.63 | L12: =F12+I12 -> 23436.24
B13: 11 | C13: Union Bank of India | D13: 47978 | E13: 63207.56 | F13: 70512.3 | G13: 21931.33 | H13: 24439.96 | I13: 25936.55 | J13: =D13+G13 -> 69909.33 | K13: =E13+H13 -> 87647.52 | L13: =F13+I13 -> 96448.85
B14: 12 | C14: State Bank of India (SBI) | D14: 187262.56 | E14: 255255 | F14: 295524 | G14: 97743.14 | H14: 117761 | I14: 118069 | J14: =D14+G14 -> 285005.7 | K14: =E14+H14 -> 373016 | L14: =F14+I14 -> 413593

Sheet Profit
B1: Sr. No. | C1: Banks | D1: Operating Profit | G1: Provision & Contingencies | J1: Net Profit
B2: I | C2: NATIONALISED BANKS | D2: 2023 | E2: 2024 | F2: 2025 | G2: 2023 | H2: 2024 | I2: 2025 | J2: 2023 | K2: 2024 | L2: 2025
B3: 1 | C3: Bank of Baroda | D3: =INCOME!K3-EXP!J3 -> 26863.54 | E3: =INCOME!L3-EXP!K3 -> 30965.22 | F3: 32434.63 | G3: =7136.9+5617.02 -> 12753.92 | H3: =6075.61+7100.83 -> 13176.44 | I3: =5980.25+6873.23 -> 12853.48 | J3: =D3-G3 -> 14109.62 | K3: =E3-H3 -> 17788.78 | L3: =F3-I3 -> 19581.15
B4: 2 | C4: Bank of India | D4: =INCOME!K4-EXP!J4 -> 13392.62 | E4: =INCOME!L4-EXP!K4 -> 14068.61 | F4: 16412.11 | G4: =7163.31+2206.37 -> 9369.68 | H4: =3969.54+3781.15 -> 7750.69 | I4: =3977.67+3215.42 -> 7193.09 | J4: =D4-G4 -> 4022.94 | K4: =E4-H4 -> 6317.92 | L4: =F4-I4 -> 9219.02
B5: 3 | C5: Bank of Maharashtra | D5: =INCOME!K5-EXP!J5 -> 6099.21 | E5: =INCOME!L5-EXP!K5 -> 8005.34 | F5: 9319.03 | G5: =2654.33+842.85 -> 3497.18 | H5: =3645.87+304.44 -> 3950.31 | I5: =202.69+3596.55 -> 3799.24 | J5: =D5-G5 -> 2602.03 | K5: =E5-H5 -> 4055.03 | L5: =F5-I5 -> 5519.79
B6: 4 | C6: Canara Bank | D6: =INCOME!K6-EXP!J6 -> 27716.01 | E6: =INCOME!L6-EXP!K6 -> 29412.59 | F6: 31390.26 | G6: =13543+3569.24 -> 17112.24 | H6: =9707.61+5150.65 -> 14858.26 | I6: =8763.59+5600 -> 14363.59 | J6: =D6-G6 -> 10603.77 | K6: =E6-H6 -> 14554.33 | L6: =F6-I6 -> 17026.67
B7: 5 | C7: Central Bank of India | D7: =INCOME!K7-EXP!J7 -> 6883.76 | E7: =INCOME!L7-EXP!K7 -> 7362.68 | F7: 8124.31 | G7: =4238.42+1063.14 -> 5301.56 | H7: =3309.3+1504.32 -> 4813.62 | I7: =3190.04+1149.01 -> 4339.05 | J7: =D7-G7 -> 1582.2 | K7: =E7-H7 -> 2549.06 | L7: =F7-I7 -> 3785.26
B8: 6 | C8: Indian Bank | D8: =INCOME!K8-EXP!J8 -> 15270.62 | E8: =INCOME!L8-EXP!K8 -> 16839.55 | F8: 18998.2 | G8: =9356.21+632.71 -> 9988.92 | H8: =5888.41+2888.2 -> 8776.61 | I8: =4211.27+3868.64 -> 8079.91 | J8: =D8-G8 -> 5281.7 | K8: =E8-H8 -> 8062.94 | L8: =F8-I8 -> 10918.29
B9: 7 | C9: Indian Overseas Bank | D9: =INCOME!K9-EXP!J9 -> 5942.18 | E9: =INCOME!L9-EXP!K9 -> 6763.76 | F9: 8688.01 | G9: =3593.93+249.46 -> 3843.39 | H9: =3351.23+756.92 -> 4108.15 | I9: =4176.29+1177.01 -> 5353.3 | J9: =D9-G9 -> 2098.79 | K9: =E9-H9 -> 2655.61 | L9: =F9-I9 -> 3334.71
B10: 8 | C10: Punjab & Sind Bank | D10: =INCOME!K10-EXP!J10 -> 1449.94 | E10: =INCOME!L10-EXP!K10 -> 1130.94 | F10: 2074.92 | G10: =-169.9+306.81 -> 136.91 | H10: =193.96+341.56 -> 535.52 | I10: =737.37+321.72 -> 1059.09 | J10: =D10-G10 -> 1313.03 | K10: =E10-H10 -> 595.42 | L10: =F10-I10 -> 1015.83
B11: 9 | C11: Punjab National Bank | D11: =INCOME!K11-EXP!J11 -> 22528.75 | E11: =INCOME!L11-EXP!K11 -> 24930.81 | F11: 26830.67 | G11: =1781.06+18240.49 -> 20021.55 | H11: =11736.6+4949.59 -> 16686.19 | I11: =8525.87+1674.6 -> 10200.47 | J11: =D11-G11 -> 2507.2 | K11: =E11-H11 -> 8244.62 | L11: =F11-I11 -> 16630.2
B12: 10 | C12: UCO Bank | D12: =INCOME!K12-EXP!J12 -> 4340.67 | E12: =INCOME!L12-EXP!K12 -> 4576.24 | F12: 6037.29 | G12: =1435.56+1042.77 -> 2478.33 | H12: =2007.39+915.11 -> 2922.5 | I12: =2203.74+1388.59 -> 3592.33 | J12: =D12-G12 -> 1862.34 | K12: =E12-H12 -> 1653.74 | L12: =F12-I12 -> 2444.96
B13: 11 | C13: Union Bank of India | D13: =INCOME!K13-EXP!J13 -> 25467.16 | E13: =INCOME!L13-EXP!K13 -> 28210.63 | F13: 31090.04 | G13: =13329.44+3704.45 -> 17033.89 | H13: =6780.24+7782.08 -> 14562.32 | I13: =7610.98+5491.92 -> 13102.9 | J13: =D13-G13 -> 8433.27 | K13: =E13-H13 -> 13648.31 | L13: =F13-I13 -> 17987.14
B14: 12 | C14: State Bank of India (SBI) | D14: =INCOME!K14-EXP!J14 -> 83712.95 | E14: =INCOME!L14-EXP!K14 -> 93797 | F14: 110579 | G14: 33480.51 | H14: =25620+7100 -> 32720 | I14: =39678 -> 39678 | J14: =D14-G14 -> 50232.44 | K14: 61077 | L14: =F14-I14 -> 70901

Sheet Ratio I
B1: Sr. No. | C1: Banks | D1: Credit Deposit Ratio | G1: Investment Deposit Ratio | J1: Spread as % Assets
B2: I | C2: NATIONALISED BANKS | D2: 2023 | E2: 2024 | F2: 2025 | G2: 2023 | H2: 2024 | I2: 2025 | J2: 2023 | K2: 2024 | L2: 2025
B3: 1 | C3: Bank of Baroda | D3: =DEPO!J3/DEPO!D3*100 -> 78.176274 | E3: =DEPO!K3/DEPO!E3*100 -> 79.825681 | F3: =DEPO!L3/DEPO!F3*100 -> 82.169108 | G3: =DEPO!G3/DEPO!D3*100 -> 30.114567 | H3: =DEPO!H3/DEPO!E3*100 -> 27.698806 | I3: =DEPO!I3/DEPO!F3*100 -> 26.18134 | J3: =(INCOME!E3-EXP!D3)/Assets!D3*100 -> 2.835397 | K3: =(INCOME!F3-EXP!E3)/Assets!E3*100 -> 2.8201294 | L3: =(INCOME!G3-EXP!F3)/Assets!F3*100 -> 2.5632982
B4: 2 | C4: Bank of India | D4: =DEPO!J4/DEPO!D4*100 -> 72.567174 | E4: =DEPO!K4/DEPO!E4*100 -> 76.315117 | F4: =DEPO!L4/DEPO!F4*100 -> 79.562037 | G4: =DEPO!G4/DEPO!D4*100 -> 30.526027 | H4: =DEPO!H4/DEPO!E4*100 -> 30.781711 | I4: =DEPO!I4/DEPO!F4*100 -> 31.732839 | J4: =(INCOME!E4-EXP!D4)/Assets!D4*100 -> 2.4860218 | K4: =(INCOME!F4-EXP!E4)/Assets!E4*100 -> 2.5260763 | L4: =(INCOME!G4-EXP!F4)/Assets!F4*100 -> 2.3397633
B5: 3 | C5: Bank of Maharashtra | D5: =DEPO!J5/DEPO!D5*100 -> 73.145382 | E5: =DEPO!K5/DEPO!E5*100 -> 73.958254 | F5: =DEPO!L5/DEPO!F5*100 -> 76.864557 | G5: =DEPO!G5/DEPO!D5*100 -> 29.419925 | H5: =DEPO!H5/DEPO!E5*100 -> 25.216928 | I5: =DEPO!I5/DEPO!F5*100 -> 26.699256 | J5: =(INCOME!E5-EXP!D5)/Assets!D5*100 -> 2.8921128 | K5: =(INCOME!F5-EXP!E5)/Assets!E5*100 -> 3.1978637 | L5: =(INCOME!G5-EXP!F5)/Assets!F5*100 -> 3.1601837
B6: 4 | C6: Canara Bank | D6: =DEPO!J6/DEPO!D6*100 -> 70.442626 | E6: =DEPO!K6/DEPO!E6*100 -> 70.98724 | F6: =DEPO!L6/DEPO!F6*100 -> 72.013668 | G6: =DEPO!G6/DEPO!D6*100 -> 27.055073 | H6: =DEPO!H6/DEPO!E6*100 -> 27.237391 | I6: =DEPO!I6/DEPO!F6*100 -> 26.106651 | J6: =(INCOME!E6-EXP!D6)/Assets!D6*100 -> 2.3359245 | K6: =(INCOME!F6-EXP!E6)/Assets!E6*100 -> 2.4515549 | L6: =(INCOME!G6-EXP!F6)/Assets!F6*100 -> 2.2029277
B7: 5 | C7: Central Bank of India | D7: =DEPO!J7/DEPO!D7*100 -> 56.494936 | E7: =DEPO!K7/DEPO!E7*100 -> 63.220552 | F7: =DEPO!L7/DEPO!F7*100 -> 68.432718 | G7: =DEPO!G7/DEPO!D7*100 -> 38.014145 | H7: =DEPO!H7/DEPO!E7*100 -> 37.381626 | I7: =DEPO!I7/DEPO!F7*100 -> 34.270955 | J7: =(INCOME!E7-EXP!D7)/Assets!D7*100 -> 2.8773469 | K7: =(INCOME!F7-EXP!E7)/Assets!E7*100 -> 2.8871969 | L7: =(INCOME!G7-EXP!F7)/Assets!F7*100 -> 2.9004538
B8: 6 | C8: Indian Bank | D8: =DEPO!J8/DEPO!D8*100 -> 72.331213 | E8: =DEPO!K8/DEPO!E8*100 -> 74.838527 | F8: =DEPO!L8/DEPO!F8*100 -> 77.469773 | G8: =DEPO!G8/DEPO!D8*100 -> 29.941807 | H8: =DEPO!H8/DEPO!E8*100 -> 30.894546 | I8: =DEPO!I8/DEPO!F8*100 -> 30.563933 | J8: =(INCOME!E8-EXP!D8)/Assets!D8*100 -> 2.8466487 | K8: =(INCOME!F8-EXP!E8)/Assets!E8*100 -> 2.9362514 | L8: =(INCOME!G8-EXP!F8)/Assets!F8*100 -> 2.8825352
B9: 7 | C9: Indian Overseas Bank | D9: =DEPO!J9/DEPO!D9*100 -> 68.249894 | E9: =DEPO!K9/DEPO!E9*100 -> 74.611681 | F9: =DEPO!L9/DEPO!F9*100 -> 78.719016 | G9: =DEPO!G9/DEPO!D9*100 -> 36.096758 | H9: =DEPO!H9/DEPO!E9*100 -> 34.847921 | I9: =DEPO!I9/DEPO!F9*100 -> 35.598275 | J9: =(INCOME!E9-EXP!D9)/Assets!D9*100 -> 2.6310757 | K9: =(INCOME!F9-EXP!E9)/Assets!E9*100 -> 2.7921793 | L9: =(INCOME!G9-EXP!F9)/Assets!F9*100 -> 2.7569109
B10: 8 | C10: Punjab & Sind Bank | D10: =DEPO!J10/DEPO!D10*100 -> 70.048864 | E10: =DEPO!K10/DEPO!E10*100 -> 69.287909 | F10: =DEPO!L10/DEPO!F10*100 -> 74.976409 | G10: =DEPO!G10/DEPO!D10*100 -> 40.886536 | H10: =DEPO!H10/DEPO!E10*100 -> 41.537013 | I10: =DEPO!I10/DEPO!F10*100 -> 36.149231 | J10: =(INCOME!E10-EXP!D10)/Assets!D10*100 -> 2.1790264 | K10: =(INCOME!F10-EXP!E10)/Assets!E10*100 -> 1.9240869 | L10: =(INCOME!G10-EXP!F10)/Assets!F10*100 -> 2.3382604
B11: 9 | C11: Punjab National Bank | D11: =DEPO!J11/DEPO!D11*100 -> 64.849977 | E11: =DEPO!K11/DEPO!E11*100 -> 68.220913 | F11: =DEPO!L11/DEPO!F11*100 -> 68.776877 | G11: =DEPO!G11/DEPO!D11*100 -> 30.909157 | H11: =DEPO!H11/DEPO!E11*100 -> 30.686594 | I11: =DEPO!I11/DEPO!F11*100 -> 31.74415 | J11: =(INCOME!E11-EXP!D11)/Assets!D11*100 -> 2.3594808 | K11: =(INCOME!F11-EXP!E11)/Assets!E11*100 -> 2.5664087 | L11: =(INCOME!G11-EXP!F11)/Assets!F11*100 -> 2.3530337
B12: 10 | C12: UCO Bank | D12: =DEPO!J12/DEPO!D12*100 -> 62.513673 | E12: =DEPO!K12/DEPO!E12*100 -> 69.175704 | F12: =DEPO!L12/DEPO!F12*100 -> 73.289154 | G12: =DEPO!G12/DEPO!D12*100 -> 38.168851 | H12: =DEPO!H12/DEPO!E12*100 -> 35.307445 | I12: =DEPO!I12/DEPO!F12*100 -> 32.115483 | J12: =(INCOME!E12-EXP!D12)/Assets!D12*100 -> 2.440689 | K12: =(INCOME!F12-EXP!E12)/Assets!E12*100 -> 2.502624 | L12: =(INCOME!G12-EXP!F12)/Assets!F12*100 -> 2.6567097
B13: 11 | C13: Union Bank of India | D13: =DEPO!J13/DEPO!D13*100 -> 68.160896 | E13: =DEPO!K13/DEPO!E13*100 -> 71.285785 | F13: =DEPO!L13/DEPO!F13*100 -> 72.801198 | G13: =DEPO!G13/DEPO!D13*100 -> 30.356455 | H13: =DEPO!H13/DEPO!E13*100 -> 27.662356 | I13: =DEPO!I13/DEPO!F13*100 -> 27.057189 | J13: =(INCOME!E13-EXP!D13)/Assets!D13*100 -> 2.5582883 | K13: =(INCOME!F13-EXP!E13)/Assets!E13*100 -> 2.6272639 | L13: =(INCOME!G13-EXP!F13)/Assets!F13*100 -> 2.48115
B14: 12 | C14: State Bank of India (SBI) | D14: =DEPO!J14/DEPO!D14*100 -> 72.319846 | E14: =DEPO!K14/DEPO!E14*100 -> 75.34404 | F14: =DEPO!L14/DEPO!F14*100 -> 77.353494 | G14: =DEPO!G14/DEPO!D14*100 -> 35.498307 | H14: =DEPO!H14/DEPO!E14*100 -> 33.997433 | I14: =DEPO!I14/DEPO!F14*100 -> 31.410504 | J14: =(INCOME!E14-EXP!D14)/Assets!D14*100 -> 2.6253591 | K14: =(INCOME!F14-EXP!E14)/Assets!E14*100 -> 2.5871184 | L14: =(INCOME!G14-EXP!F14)/Assets!F14*100 -> 2.5009538

Sheet Ratio II
B1: Statement VII : Public Sector Banks : Ratios
B2: As on March 31 | D2: (In Per Cent)
B3: Sr. No. | C3: Banks | D3: Operating Expenses as % to Total Expenses | G3: Return on Assets [%] | J3: Capital Adequacy Ratio-Basel III [%] | N3: Provision Coverage Ratio (PCR %)
B4: I | C4: NATIONALISED BANKS | D4: 2023 | E4: 2024 | F4: 2025 | G4: 2023 | H4: 2024 | I4: 2025 | J4: 2023 | K4: 2024 | L4: 2025 | N4: 2023 | O4: 2024 | P4: 2025
B5: 1 | C5: Bank of Baroda | D5: =EXP!G3/EXP!J3*100 -> 33.701755 | E5: =EXP!H3/EXP!K3*100 -> 29.387174 | F5: =EXP!I3/EXP!L3*100 -> 28.272743 | G5: 1.03 | H5: 1.17 | I5: 1.16 | J5: 16.24 | K5: 16.31 | L5: 17.19 | N5: 92.43 | O5: 93.3 | P5: 93.29 | Q5: =EXP!G3/EXP!J3*100-'Ratio II'!D5 -> 0 | R5: =EXP!H3/EXP!K3*100-'Ratio II'!E5 -> 0 | S5: =EXP!I3/EXP!L3*100-'Ratio II'!F5 -> 0
B6: 2 | C6: Bank of India | D6: =EXP!G4/EXP!J4*100 -> 33.810116 | E6: =EXP!H4/EXP!K4*100 -> 28.593821 | F6: =EXP!I4/EXP!L4*100 -> 26.771876 | G6: 0.49 | H6: 0.7 | I6: 0.9 | J6: 16.28 | K6: 16.96 | L6: 17.77 | N6: 89.68 | O6: 90.59 | P6: 92.39 | Q6: =EXP!G4/EXP!J4*100-'Ratio II'!D6 -> 0 | R6: =EXP!H4/EXP!K4*100-'Ratio II'!E6 -> 0 | S6: =EXP!I4/EXP!L4*100-'Ratio II'!F6 -> 0
B7: 3 | C7: Bank of Maharashtra | D7: =EXP!G5/EXP!J5*100 -> 32.466853 | E7: =EXP!H5/EXP!K5*100 -> 31.086147 | F7: =EXP!I5/EXP!L5*100 -> 30.397918 | G7: 1.1 | H7: 1.5 | I7: 1.75 | J7: 18.14 | K7: 17.38 | L7: 20.53 | N7: 98.28 | O7: 98.34 | P7: 98.26 | Q7: =EXP!G5/EXP!J5*100-'Ratio II'!D7 -> 0 | R7: =EXP!H5/EXP!K5*100-'Ratio II'!E7 -> 0 | S7: =EXP!I5/EXP!L5*100-'Ratio II'!F7 -> 0
B8: 4 | C8: Canara Bank | D8: =EXP!G6/EXP!J6*100 -> 29.788248 | E8: =EXP!H6/EXP!K6*100 -> 26.587252 | F8: =EXP!I6/EXP!L6*100 -> 25.388113 | G8: 0.81 | H8: 1.01 | I8: 1.09 | J8: 16.68 | K8: 16.28 | L8: 16.33 | N8: 87.31 | O8: 89.1 | P8: 92.7 | Q8: =EXP!G6/EXP!J6*100-'Ratio II'!D8 -> 0 | R8: =EXP!H6/EXP!K6*100-'Ratio II'!E8 -> 0 | S8: =EXP!I6/EXP!L6*100-'Ratio II'!F8 -> 0
B9: 5 | C9: Central Bank of India | D9: =EXP!G7/EXP!J7*100 -> 39.076609 | E9: =EXP!H7/EXP!K7*100 -> 36.496676 | F9: =EXP!I7/EXP!L7*100 -> 37.033768 | G9: 0.44 | H9: 0.63 | I9: 0.86 | J9: 14.12 | K9: 15.08 | L9: 17.02 | N9: 92.48 | O9: 93.58 | P9: 96.54 | Q9: =EXP!G7/EXP!J7*100-'Ratio II'!D9 -> 0 | R9: =EXP!H7/EXP!K7*100-'Ratio II'!E9 -> 0 | S9: =EXP!I7/EXP!L7*100-'Ratio II'!F9 -> 0
B10: 6 | C10: Indian Bank | D10: =EXP!G8/EXP!J8*100 -> 32.861646 | E10: =EXP!H8/EXP!K8*100 -> 30.660082 | F10: =EXP!I8/EXP!L8*100 -> 29.489575 | G10: 0.77 | H10: 1.07 | I10: 1.32 | J10: 16.49 | K10: 16.44 | L10: 17.94 | N10: 93.82 | O10: 96.34 | P10: 98.1 | Q10: =EXP!G8/EXP!J8*100-'Ratio II'!D10 -> 0 | R10: =EXP!H8/EXP!K8*100-'Ratio II'!E10 -> 0 | S10: =EXP!I8/EXP!L8*100-'Ratio II'!F10 -> 0
B11: 7 | C11: Indian Overseas Bank | D11: =EXP!G9/EXP!J9*100 -> 36.554315 | E11: =EXP!H9/EXP!K9*100 -> 38.016836 | F11: =EXP!I9/EXP!L9*100 -> 31.003875 | G11: 0.68 | H11: 0.81 | I11: 0.92 | J11: 16.1 | K11: 17.28 | L11: 19.74 | N11: 92.63 | O11: 96.85 | P11: 97.3 | Q11: =EXP!G9/EXP!J9*100-'Ratio II'!D11 -> 0 | R11: =EXP!H9/EXP!K9*100-'Ratio II'!E11 -> 0 | S11: =EXP!I9/EXP!L9*100-'Ratio II'!F11 -> 0
B12: 8 | C12: Punjab & Sind Bank | D12: =EXP!G10/EXP!J10*100 -> 32.921052 | E12: =EXP!H10/EXP!K10*100 -> 29.961337 | F12: =EXP!I10/EXP!L10*100 -> 29.855851 | G12: 0.98 | H12: 0.41 | I12: 0.67 | J12: 17.1 | K12: 17.16 | L12: 17.41 | N12: 89.06 | O12: 88.69 | P12: 91.38 | Q12: =EXP!G10/EXP!J10*100-'Ratio II'!D12 -> 0 | R12: =EXP!H10/EXP!K10*100-'Ratio II'!E12 -> 0 | S12: =EXP!I10/EXP!L10*100-'Ratio II'!F12 -> 0
B13: 9 | C13: Punjab National Bank | D13: =EXP!G11/EXP!J11*100 -> 32.244637 | E13: =EXP!H11/EXP!K11*100 -> 29.92606 | F13: =EXP!I11/EXP!L11*100 -> 29.00129 | G13: 0.18 | H13: 0.54 | I13: 0.97 | J13: 15.5 | K13: 15.97 | L13: 17.01 | N13: 86.9 | O13: 95.39 | P13: 96.82 | Q13: =EXP!G11/EXP!J11*100-'Ratio II'!D13 -> 0 | R13: =EXP!H11/EXP!K11*100-'Ratio II'!E13 -> 0 | S13: =EXP!I11/EXP!L11*100-'Ratio II'!F13 -> 0
B14: 10 | C14: UCO Bank | D14: =EXP!G12/EXP!J12*100 -> 34.838867 | E14: =EXP!H12/EXP!K12*100 -> 33.051948 | F14: =EXP!I12/EXP!L12*100 -> 34.132651 | G14: 0.62 | H14: 0.56 | I14: 0.76 | J14: 16.51 | K14: 16.98 | L14: 18.49 | N14: 94.5 | O14: 95.38 | P14: 96.69 | Q14: =EXP!G12/EXP!J12*100-'Ratio II'!D14 -> 0 | R14: =EXP!H12/EXP!K12*100-'Ratio II'!E14 -> 0 | S14: =EXP!I12/EXP!L12*100-'Ratio II'!F14 -> 0
B15: 11 | C15: Union Bank of India | D15: =EXP!G13/EXP!J13*100 -> 31.371106 | E15: =EXP!H13/EXP!K13*100 -> 27.884371 | F15: =EXP!I13/EXP!L13*100 -> 26.891508 | G15: 0.69 | H15: 1.03 | I15: 1.26 | J15: 16.04 | K15: 16.97 | L15: 18.02 | N15: 90.34 | O15: 92.69 | P15: 94.61 | Q15: =EXP!G13/EXP!J13*100-'Ratio II'!D15 -> 0 | R15: =EXP!H13/EXP!K13*100-'Ratio II'!E15 -> 0 | S15: =EXP!I13/EXP!L13*100-'Ratio II'!F15 -> 0
B16: 12 | C16: State Bank of India (SBI) | D16: =EXP!#REF!/EXP!#REF!*100 -> #REF! | E16: =EXP!#REF!/EXP!#REF!*100 -> #REF! | F16: =EXP!#REF!/EXP!#REF!*100 -> #REF! | G16: 0.96 | H16: 1.04 | I16: 1.1 | J16: 14.68 | K16: 14.28 | L16: 14.25 | N16: 91.91 | O16: 91.89 | P16: 92.08 | Q16: =EXP!#REF!/EXP!#REF!*100-'Ratio II'!D16 -> #REF! | R16: =EXP!#REF!/EXP!#REF!*100-'Ratio II'!E16 -> #REF! | S16: =EXP!#REF!/EXP!#REF!*100-'Ratio II'!F16 -> #REF!
C17: TOTAL OF PUBLIC SECTOR BANKS [I+II] | D17: =EXP!G14/EXP!J14*100 -> 34.295153 | E17: =EXP!H14/EXP!K14*100 -> 31.569959 | F17: =EXP!I14/EXP!L14*100 -> 28.547147 | Q17: =EXP!G14/EXP!J14*100-'Ratio II'!D17 -> 0 | R17: =EXP!H14/EXP!K14*100-'Ratio II'!E17 -> 0 | S17: =EXP!I14/EXP!L14*100-'Ratio II'!F17 -> 0
B20: 7

Sheet NetNPAtoNetADV
A1: Sr. No. | B1: Banks | C1: Net NPA as % to Net Advances | F1: Business per Employee | I1: Profit per Employee
A2: I | B2: NATIONALISED BANKS | C2: 2023 | D2: 2024 | E2: 2025 | F2: 2023 | G2: 2024 | H2: 2025 | I2: 2023 | J2: 2024 | K2: 2025
A3: 1 | B3: Bank of Baroda | C3: =Assets!J3/DEPO!J3*100 -> 0.8910027 | D3: 0.68 | E3: 0.58 | F3: 26.66 | G3: 30.46 | H3: 34.33 | I3: 18.06 | J3: 23.56 | K3: 26.11
A4: 2 | B4: Bank of India | C4: =Assets!J4/DEPO!J4*100 -> 1.6574637 | D4: 1.22 | E4: 0.82 | F4: 22.47 | G4: 25.87 | H4: 29.19 | I4: 7.6 | J4: 12.35 | K4: 18.15
A5: 3 | B5: Bank of Maharashtra | C5: =Assets!J5/DEPO!J5*100 -> 0.25416324 | D5: 0.2 | E5: 0.18 | F5: 31.45 | G5: 35 | H5: 37.44 | I5: 20.05 | J5: 30.04 | K5: 37.83
A6: 4 | B6: Canara Bank | C6: =Assets!J6/DEPO!J6*100 -> 1.7274352 | D6: 1.27 | E6: 0.7 | F6: 22.45 | G6: 25.97 | H6: 29.3 | I6: 12 | J6: 18 | K6: 21
A7: 5 | B7: Central Bank of India | C7: =Assets!J7/DEPO!J7*100 -> 1.786946 | D7: 1.23 | E7: =Assets!L7/DEPO!L7*100 -> 0.54644172 | F7: 18.45 | G7: 20.14 | H7: 21.24 | I7: 5.07 | J7: 8.06 | K7: 10.13
A8: 6 | B8: Indian Bank | C8: =Assets!J8/DEPO!J8*100 -> 0.89986633 | D8: 0.43 | E8: =Assets!L8/DEPO!L8*100 -> 0.19429452 | F8: 26.61 | G8: 29.85 | H8: 32.42 | I8: 14.2 | J8: 20.03 | K8: 27.25
A9: 7 | B9: Indian Overseas Bank | C9: =Assets!J9/DEPO!J9*100 -> 1.8342953 | D9: 0.57 | E9: =Assets!L9/DEPO!L9*100 -> 0.37134628 | F9: 20.21 | G9: 23.54 | H9: 26.8 | I9: 9 | J9: 12 | K9: 16
A10: 8 | B10: Punjab & Sind Bank | C10: =Assets!J10/DEPO!J10*100 -> 1.8374258 | D10: 1.63 | E10: =Assets!L10/DEPO!L10*100 -> 0.96307396 | F10: 21.45 | G10: 23.35 | H10: 25.71 | I10: 14.81 | J10: 6.8 | K10: 11.45
A11: 9 | B11: Punjab National Bank | C11: =Assets!J11/DEPO!J11*100 -> 2.7183578 | D11: 0.73 | E11: =Assets!L11/DEPO!L11*100 -> 0.39820429 | F11: 21.64 | G11: 23.84 | H11: 26.86 | I11: 2.57 | J11: 8.61 | K11: 17.29
A12: 10 | B12: UCO Bank | C12: =Assets!J12/DEPO!J12*100 -> 1.29468 | D12: 0.89 | E12: =Assets!L12/DEPO!L12*100 -> 0.49647992 | F12: 18.9 | G12: 20.93 | H12: 24.35 | I12: 8.56 | J12: 7.69 | K12: 11.59
A13: 11 | B13: Union Bank of India | C13: =Assets!J13/DEPO!J13*100 -> 1.6968586 | D13: 1.03 | E13: =Assets!L13/DEPO!L13*100 -> 0.62603109 | F13: 25.5 | G13: 28.02 | H13: 31 | I13: 11.16 | J13: 17.99 | K13: 24.33
A14: 12 | B14: State Bank of India (SBI) | C14: =Assets!J14/DEPO!J14*100 -> 0.67098572 | D14: 0.57 | E14: 0.47 | F14: 29.78 | G14: 34.1 | H14: 37.37 | I14: 21.23 | J14: 26.2 | K14: 29.91
